clickhouse_migrator/__init__.py
clickhouse_migrator/cli.py
clickhouse_migrator/py.typed
clickhouse_migrator/core/__init__.py
clickhouse_migrator/core/config.py
clickhouse_migrator/core/connection.py
clickhouse_migrator/core/migrator.py
clickhouse_migrator/utils/__init__.py
clickhouse_migrator/utils/exceptions.py
clickhouse_migrator/utils/progress.py
clickhouse_migrator/utils/schema_transformer.py
hawky_clickhouse_migrator-1.0.0.dist-info/licenses/LICENSE
hawky_clickhouse_migrator-1.0.0.dist-info/METADATA
hawky_clickhouse_migrator-1.0.0.dist-info/WHEEL
hawky_clickhouse_migrator-1.0.0.dist-info/entry_points.txt
hawky_clickhouse_migrator-1.0.0.dist-info/top_level.txt
hawky_clickhouse_migrator-1.0.0.dist-info/RECORD
