Metadata-Version: 2.4
Name: hawky-clickhouse-migrator
Version: 1.0.0
Summary: A reliable CLI tool for migrating data between ClickHouse instances
Author-email: ClickHouse Migration Team <contact@clickhouse-migrator.dev>
License: MIT License
Project-URL: Homepage, https://github.com/hawky-ai/clickhouse-migrator
Project-URL: Documentation, https://github.com/hawky-ai/clickhouse-migrator#readme
Project-URL: Repository, https://github.com/hawky-ai/clickhouse-migrator.git
Project-URL: Bug Tracker, https://github.com/hawky-ai/clickhouse-migrator/issues
Keywords: clickhouse,migration,database,cli,backup,transfer
Classifier: Development Status :: 5 - Production/Stable
Classifier: Environment :: Console
Classifier: Intended Audience :: Developers
Classifier: Intended Audience :: System Administrators
Classifier: License :: OSI Approved :: MIT License
Classifier: Operating System :: OS Independent
Classifier: Programming Language :: Python :: 3
Classifier: Programming Language :: Python :: 3.8
Classifier: Programming Language :: Python :: 3.9
Classifier: Programming Language :: Python :: 3.10
Classifier: Programming Language :: Python :: 3.11
Classifier: Programming Language :: Python :: 3.12
Classifier: Topic :: Database
Classifier: Topic :: System :: Archiving :: Backup
Classifier: Topic :: System :: Systems Administration
Classifier: Topic :: Utilities
Requires-Python: >=3.8
License-File: LICENSE
Requires-Dist: clickhouse-connect>=0.6.0
Requires-Dist: click>=8.0.0
Requires-Dist: rich>=13.0.0
Requires-Dist: tqdm>=4.64.0
Requires-Dist: pydantic>=2.0.0
Requires-Dist: tenacity>=8.0.0
Requires-Dist: PyYAML>=6.0
Requires-Dist: psutil>=5.9.0
Provides-Extra: dev
Requires-Dist: pytest>=7.0.0; extra == "dev"
Requires-Dist: pytest-cov>=4.0.0; extra == "dev"
Requires-Dist: pytest-asyncio>=0.21.0; extra == "dev"
Requires-Dist: black>=23.0.0; extra == "dev"
Requires-Dist: isort>=5.12.0; extra == "dev"
Requires-Dist: flake8>=6.0.0; extra == "dev"
Requires-Dist: mypy>=1.0.0; extra == "dev"
Requires-Dist: pre-commit>=3.0.0; extra == "dev"
Dynamic: license-file
